{
  "schema_version": "1.0",
  "catalog_key": "hublot-00527",
  "source_sku_id": "00527",
  "candidate_sku_key": "hublot-00527",
  "single_sku_lock": {
    "model": "RW.1104",
    "color": [],
    "quantity": 1,
    "status": "confirmed"
  },
  "source_brand_folder": "HUBLOT宇舶",
  "offer_id": "WT-HUBLOT-00527",
  "facts": {
    "model": {
      "value": "RW.1104",
      "status": "confirmed",
      "evidence": "description_or_catalog_sku"
    },
    "color": {
      "value": [],
      "status": "missing_noncritical",
      "evidence": "description"
    },
    "gender": {
      "value": [
        "мужские"
      ],
      "dictionary_value_ids": [
        22880
      ],
      "status": "confirmed",
      "evidence": "description_or_diameter"
    },
    "movement": {
      "value": "механический с автоподзаводом",
      "status": "confirmed",
      "evidence": "description"
    },
    "display": {
      "value": "аналоговый",
      "status": "confirmed",
      "evidence": "description_or_watch_default"
    },
    "dial": {
      "value": null,
      "status": "missing_noncritical",
      "evidence": "description"
    },
    "case": {
      "value": "нержавеющая сталь",
      "status": "confirmed",
      "evidence": "description"
    },
    "strap": {
      "value": "натуральная кожа",
      "status": "confirmed",
      "evidence": "description"
    },
    "glass": {
      "value": null,
      "status": "missing_noncritical",
      "evidence": "description"
    },
    "water_resistance": {
      "value": "46 M",
      "status": "confirmed",
      "evidence": "description"
    },
    "case_diameter_mm": {
      "value": 46.0,
      "status": "confirmed",
      "evidence": "description"
    },
    "quantity": {
      "value": 1,
      "status": "confirmed",
      "evidence": "one_sku_one_watch_contract"
    },
    "package_contents": {
      "value": "часы",
      "status": "estimated",
      "evidence": "description"
    },
    "organization_brand": {
      "value": "HUBLOT",
      "status": "confirmed",
      "evidence": "source_brand_folder"
    }
  },
  "estimated_facts": {
    "packaged_weight_g": {
      "value": 900,
      "status": "estimated",
      "estimate_basis": "user watch catalog default 600-900 g; conservative upper bound",
      "confidence": "medium",
      "risk_note": "not buyer-visible marketing copy",
      "confirmation_required": true
    },
    "package_dimensions_cm": {
      "value": {
        "length": 30,
        "width": 15,
        "height": 10
      },
      "status": "estimated",
      "estimate_basis": "watch with retail packaging",
      "confidence": "medium",
      "risk_note": "must be rechecked if packaging changes",
      "confirmation_required": true
    },
    "domestic_shipping_cny": {
      "value": 0,
      "status": "estimated",
      "estimate_basis": "user inventory rule",
      "confidence": "high",
      "risk_note": "internal calculation only",
      "confirmation_required": false
    }
  },
  "unknown_fields": [
    "color",
    "dial",
    "glass"
  ],
  "evidence": {
    "description_sha256": "4bc45f88153d027c72fc852e5fecc86458d9839ca7a0a85e0f1878ae8d8fa251",
    "images": [
      {
        "file": "1.jpg",
        "sha256": "5cc78afe5c60130407b575188eda281dae21d3afdb544d4224320773311a0108",
        "byte_size": 578039,
        "width": 1920,
        "height": 1440,
        "format": "jpg",
        "status": "confirmed",
        "is_main": true,
        "public_url": "https://raw.githubusercontent.com/ajificemey278-ctrl/ozon-watch-product-catalog/main/products/hublot/00527/1.jpg"
      },
      {
        "file": "2.jpg",
        "sha256": "f42e89a32049fb2fd62897c6f60eeeabd109b1cd713178fa8b3514ab1303919b",
        "byte_size": 611064,
        "width": 1920,
        "height": 1440,
        "format": "jpg",
        "status": "confirmed",
        "is_main": false,
        "public_url": "https://raw.githubusercontent.com/ajificemey278-ctrl/ozon-watch-product-catalog/main/products/hublot/00527/2.jpg"
      },
      {
        "file": "3.jpg",
        "sha256": "098d582aee2b23d18460ca6471dbf809bd8d03bc7029f7f423b7f283089ba230",
        "byte_size": 629045,
        "width": 1920,
        "height": 1440,
        "format": "jpg",
        "status": "confirmed",
        "is_main": false,
        "public_url": "https://raw.githubusercontent.com/ajificemey278-ctrl/ozon-watch-product-catalog/main/products/hublot/00527/3.jpg"
      },
      {
        "file": "4.jpg",
        "sha256": "c6038dc92df11aa2411679e1973feb9f032ca6dfcd2fbfdb4bf5993b63b87f99",
        "byte_size": 628327,
        "width": 1920,
        "height": 1440,
        "format": "jpg",
        "status": "confirmed",
        "is_main": false,
        "public_url": "https://raw.githubusercontent.com/ajificemey278-ctrl/ozon-watch-product-catalog/main/products/hublot/00527/4.jpg"
      },
      {
        "file": "5.jpg",
        "sha256": "58e7b8bae9b23ae3f2093c4f45a15ead6d8b20f3af70042dc4ec92b55d099476",
        "byte_size": 529628,
        "width": 1920,
        "height": 1440,
        "format": "jpg",
        "status": "confirmed",
        "is_main": false,
        "public_url": "https://raw.githubusercontent.com/ajificemey278-ctrl/ozon-watch-product-catalog/main/products/hublot/00527/5.jpg"
      },
      {
        "file": "6.jpg",
        "sha256": "fbcebab0de1b48d470cf73631e9d56abc0f0bd94a4ad502c540feaa3128ec4ed",
        "byte_size": 597762,
        "width": 1920,
        "height": 1440,
        "format": "jpg",
        "status": "confirmed",
        "is_main": false,
        "public_url": "https://raw.githubusercontent.com/ajificemey278-ctrl/ozon-watch-product-catalog/main/products/hublot/00527/6.jpg"
      },
      {
        "file": "7.jpg",
        "sha256": "43188ac1e41192d426bb8d004e476c3ae1daf2493ce582d2b97aa7f2d4b4af6d",
        "byte_size": 529945,
        "width": 1920,
        "height": 1440,
        "format": "jpg",
        "status": "confirmed",
        "is_main": false,
        "public_url": "https://raw.githubusercontent.com/ajificemey278-ctrl/ozon-watch-product-catalog/main/products/hublot/00527/7.jpg"
      },
      {
        "file": "8.jpg",
        "sha256": "106213020b45d3c324e6b32cfb1f16ea8aae63de5e0f510e7f6dd66cc77b5489",
        "byte_size": 593824,
        "width": 1920,
        "height": 1440,
        "format": "jpg",
        "status": "confirmed",
        "is_main": false,
        "public_url": "https://raw.githubusercontent.com/ajificemey278-ctrl/ozon-watch-product-catalog/main/products/hublot/00527/8.jpg"
      },
      {
        "file": "9.jpg",
        "sha256": "b377c029d61100e23a30ab0edbcdb8c463f90a0d9aa63b44fc880c6170b047a9",
        "byte_size": 550412,
        "width": 1920,
        "height": 1440,
        "format": "jpg",
        "status": "confirmed",
        "is_main": false,
        "public_url": "https://raw.githubusercontent.com/ajificemey278-ctrl/ozon-watch-product-catalog/main/products/hublot/00527/9.jpg"
      }
    ]
  }
}
