{
  "schema_version": "1.0",
  "catalog_key": "omega-00205",
  "source_sku_id": "00205",
  "candidate_sku_key": "omega-00205",
  "single_sku_lock": {
    "model": "WT-00205",
    "color": [],
    "quantity": 1,
    "status": "confirmed"
  },
  "source_brand_folder": "OMEGA欧米茄",
  "offer_id": "WT-OMEGA-00205",
  "facts": {
    "model": {
      "value": "WT-00205",
      "status": "estimated",
      "evidence": "description_or_catalog_sku"
    },
    "color": {
      "value": [],
      "status": "missing_noncritical",
      "evidence": "description"
    },
    "gender": {
      "value": [
        "мужские",
        "женские"
      ],
      "dictionary_value_ids": [
        22880,
        22881
      ],
      "status": "estimated",
      "evidence": "description_or_diameter"
    },
    "movement": {
      "value": null,
      "status": "missing_noncritical",
      "evidence": "description"
    },
    "display": {
      "value": "аналоговый",
      "status": "estimated",
      "evidence": "description_or_watch_default"
    },
    "dial": {
      "value": null,
      "status": "missing_noncritical",
      "evidence": "description"
    },
    "case": {
      "value": null,
      "status": "missing_noncritical",
      "evidence": "description"
    },
    "strap": {
      "value": null,
      "status": "missing_noncritical",
      "evidence": "description"
    },
    "glass": {
      "value": null,
      "status": "missing_noncritical",
      "evidence": "description"
    },
    "water_resistance": {
      "value": null,
      "status": "missing_noncritical",
      "evidence": "description"
    },
    "case_diameter_mm": {
      "value": null,
      "status": "missing_noncritical",
      "evidence": "description"
    },
    "quantity": {
      "value": 1,
      "status": "confirmed",
      "evidence": "one_sku_one_watch_contract"
    },
    "package_contents": {
      "value": "часы и комплект упаковки",
      "status": "confirmed",
      "evidence": "description"
    },
    "organization_brand": {
      "value": "OMEGA",
      "status": "confirmed",
      "evidence": "source_brand_folder"
    }
  },
  "estimated_facts": {
    "packaged_weight_g": {
      "value": 900,
      "status": "estimated",
      "estimate_basis": "user watch catalog default 600-900 g; conservative upper bound",
      "confidence": "medium",
      "risk_note": "not buyer-visible marketing copy",
      "confirmation_required": true
    },
    "package_dimensions_cm": {
      "value": {
        "length": 30,
        "width": 15,
        "height": 10
      },
      "status": "estimated",
      "estimate_basis": "watch with retail packaging",
      "confidence": "medium",
      "risk_note": "must be rechecked if packaging changes",
      "confirmation_required": true
    },
    "domestic_shipping_cny": {
      "value": 0,
      "status": "estimated",
      "estimate_basis": "user inventory rule",
      "confidence": "high",
      "risk_note": "internal calculation only",
      "confirmation_required": false
    }
  },
  "unknown_fields": [
    "color",
    "movement",
    "dial",
    "case",
    "strap",
    "glass",
    "water_resistance",
    "case_diameter_mm"
  ],
  "evidence": {
    "description_sha256": "64e91b6354ae9609ec86c48b7c7ec31e8fb108faca90a7df5e0a7d59ee9a359f",
    "images": [
      {
        "file": "1.jpg",
        "sha256": "30883973b3045c6cf4c95c6879738573119a04b4c1d35a5073bc246c911b53f0",
        "byte_size": 482324,
        "width": 1440,
        "height": 1920,
        "format": "jpg",
        "status": "confirmed",
        "is_main": true,
        "public_url": "https://raw.githubusercontent.com/ajificemey278-ctrl/ozon-watch-product-catalog/main/products/omega/00205/1.jpg"
      },
      {
        "file": "2.jpg",
        "sha256": "3b2c7212fd4e5f7b5ffe51b856c9d769cc6476af12acaa0612e28ee7a1e7c327",
        "byte_size": 471841,
        "width": 1442,
        "height": 1922,
        "format": "jpg",
        "status": "confirmed",
        "is_main": false,
        "public_url": "https://raw.githubusercontent.com/ajificemey278-ctrl/ozon-watch-product-catalog/main/products/omega/00205/2.jpg"
      },
      {
        "file": "3.jpg",
        "sha256": "adacc3941827ee12ef655509b77396e133ffe14ed9273ba270c13587453669ea",
        "byte_size": 430953,
        "width": 1442,
        "height": 1922,
        "format": "jpg",
        "status": "confirmed",
        "is_main": false,
        "public_url": "https://raw.githubusercontent.com/ajificemey278-ctrl/ozon-watch-product-catalog/main/products/omega/00205/3.jpg"
      },
      {
        "file": "4.jpg",
        "sha256": "6fe1e803ae3b7964cce62f58bbe696bcaf6fb95acf80374c05ba02790b8d5d94",
        "byte_size": 484643,
        "width": 1442,
        "height": 1922,
        "format": "jpg",
        "status": "confirmed",
        "is_main": false,
        "public_url": "https://raw.githubusercontent.com/ajificemey278-ctrl/ozon-watch-product-catalog/main/products/omega/00205/4.jpg"
      },
      {
        "file": "5.jpg",
        "sha256": "c2dad0689c3c8b66ae085cbb938e194053fd9e9084bc7aebd0190db50e3a9b34",
        "byte_size": 430101,
        "width": 1442,
        "height": 1922,
        "format": "jpg",
        "status": "confirmed",
        "is_main": false,
        "public_url": "https://raw.githubusercontent.com/ajificemey278-ctrl/ozon-watch-product-catalog/main/products/omega/00205/5.jpg"
      },
      {
        "file": "6.jpg",
        "sha256": "a55d5955a478dc3046f1f4d8d8dcd4fa0f57260d4eeaeac8f9f5abeeac219222",
        "byte_size": 483344,
        "width": 1442,
        "height": 1922,
        "format": "jpg",
        "status": "confirmed",
        "is_main": false,
        "public_url": "https://raw.githubusercontent.com/ajificemey278-ctrl/ozon-watch-product-catalog/main/products/omega/00205/6.jpg"
      },
      {
        "file": "7.jpg",
        "sha256": "d0a4827a00e3aed37d1e517257dcb1ae2f91872ddba5f4c7eef73e20c643445b",
        "byte_size": 467881,
        "width": 1440,
        "height": 1920,
        "format": "jpg",
        "status": "confirmed",
        "is_main": false,
        "public_url": "https://raw.githubusercontent.com/ajificemey278-ctrl/ozon-watch-product-catalog/main/products/omega/00205/7.jpg"
      },
      {
        "file": "8.jpg",
        "sha256": "a4536cc22cb89df0aeb11b8c1fad37f995b9b4b7c904ba56ada784b4e34fc6d6",
        "byte_size": 467361,
        "width": 1442,
        "height": 1922,
        "format": "jpg",
        "status": "confirmed",
        "is_main": false,
        "public_url": "https://raw.githubusercontent.com/ajificemey278-ctrl/ozon-watch-product-catalog/main/products/omega/00205/8.jpg"
      },
      {
        "file": "9.jpg",
        "sha256": "69a02c7a8e9ca6d16edb42c7b40b343a6c8e5db7053ea4036c591898de0203c7",
        "byte_size": 481308,
        "width": 1440,
        "height": 1920,
        "format": "jpg",
        "status": "confirmed",
        "is_main": false,
        "public_url": "https://raw.githubusercontent.com/ajificemey278-ctrl/ozon-watch-product-catalog/main/products/omega/00205/9.jpg"
      }
    ]
  }
}
