{
  "schema_version": "1.0",
  "catalog_key": "longines-00234",
  "source_sku_id": "00234",
  "candidate_sku_key": "longines-00234",
  "single_sku_lock": {
    "model": "WT-00234",
    "color": [],
    "quantity": 1,
    "status": "confirmed"
  },
  "source_brand_folder": "LONGINES浪琴",
  "offer_id": "WT-LONGINES-00234",
  "facts": {
    "model": {
      "value": "WT-00234",
      "status": "estimated",
      "evidence": "description_or_catalog_sku"
    },
    "color": {
      "value": [],
      "status": "missing_noncritical",
      "evidence": "description"
    },
    "gender": {
      "value": [
        "женские"
      ],
      "dictionary_value_ids": [
        22881
      ],
      "status": "confirmed",
      "evidence": "description_or_diameter"
    },
    "movement": {
      "value": "кварцевый",
      "status": "confirmed",
      "evidence": "description"
    },
    "display": {
      "value": "аналоговый",
      "status": "confirmed",
      "evidence": "description_or_watch_default"
    },
    "dial": {
      "value": null,
      "status": "missing_noncritical",
      "evidence": "description"
    },
    "case": {
      "value": null,
      "status": "missing_noncritical",
      "evidence": "description"
    },
    "strap": {
      "value": "нержавеющая сталь",
      "status": "confirmed",
      "evidence": "description"
    },
    "glass": {
      "value": null,
      "status": "missing_noncritical",
      "evidence": "description"
    },
    "water_resistance": {
      "value": null,
      "status": "missing_noncritical",
      "evidence": "description"
    },
    "case_diameter_mm": {
      "value": null,
      "status": "missing_noncritical",
      "evidence": "description"
    },
    "quantity": {
      "value": 1,
      "status": "confirmed",
      "evidence": "one_sku_one_watch_contract"
    },
    "package_contents": {
      "value": "часы и комплект упаковки",
      "status": "confirmed",
      "evidence": "description"
    },
    "organization_brand": {
      "value": "LONGINES",
      "status": "confirmed",
      "evidence": "source_brand_folder"
    }
  },
  "estimated_facts": {
    "packaged_weight_g": {
      "value": 900,
      "status": "estimated",
      "estimate_basis": "user watch catalog default 600-900 g; conservative upper bound",
      "confidence": "medium",
      "risk_note": "not buyer-visible marketing copy",
      "confirmation_required": true
    },
    "package_dimensions_cm": {
      "value": {
        "length": 30,
        "width": 15,
        "height": 10
      },
      "status": "estimated",
      "estimate_basis": "watch with retail packaging",
      "confidence": "medium",
      "risk_note": "must be rechecked if packaging changes",
      "confirmation_required": true
    },
    "domestic_shipping_cny": {
      "value": 0,
      "status": "estimated",
      "estimate_basis": "user inventory rule",
      "confidence": "high",
      "risk_note": "internal calculation only",
      "confirmation_required": false
    }
  },
  "unknown_fields": [
    "color",
    "dial",
    "case",
    "glass",
    "water_resistance",
    "case_diameter_mm"
  ],
  "evidence": {
    "description_sha256": "be6fe6339dc4fd9cfe47a66ba6b00657a3022f78e3370769aaecb2fb467451ea",
    "images": [
      {
        "file": "1.jpg",
        "sha256": "afd814e4b659ee5547423ad8c097453b3b7321829baac4f9b9d0c94cee078541",
        "byte_size": 498198,
        "width": 1440,
        "height": 1440,
        "format": "jpg",
        "status": "confirmed",
        "is_main": true,
        "public_url": "https://raw.githubusercontent.com/ajificemey278-ctrl/ozon-watch-product-catalog/main/products/longines/00234/1.jpg"
      },
      {
        "file": "2.jpg",
        "sha256": "bb8b31af085c2078e443788099457fa80f77b3fa88429df0c041ce5a9db65dd1",
        "byte_size": 566688,
        "width": 1440,
        "height": 1440,
        "format": "jpg",
        "status": "confirmed",
        "is_main": false,
        "public_url": "https://raw.githubusercontent.com/ajificemey278-ctrl/ozon-watch-product-catalog/main/products/longines/00234/2.jpg"
      },
      {
        "file": "3.jpg",
        "sha256": "5d375a9a5c78fb7e4d7afabdc4fe808c79fe4d3afd36df54bf63de38d087a876",
        "byte_size": 526966,
        "width": 1440,
        "height": 1440,
        "format": "jpg",
        "status": "confirmed",
        "is_main": false,
        "public_url": "https://raw.githubusercontent.com/ajificemey278-ctrl/ozon-watch-product-catalog/main/products/longines/00234/3.jpg"
      },
      {
        "file": "4.jpg",
        "sha256": "9c8fe78a87b114e9787ed4e3d7bde6cf6e0fa23713bca1bc2b13239ec772361c",
        "byte_size": 503168,
        "width": 1440,
        "height": 1440,
        "format": "jpg",
        "status": "confirmed",
        "is_main": false,
        "public_url": "https://raw.githubusercontent.com/ajificemey278-ctrl/ozon-watch-product-catalog/main/products/longines/00234/4.jpg"
      },
      {
        "file": "5.jpg",
        "sha256": "7bc479281a219f7a70408b65bab7036b05846a0f4a42d6c65c2bd1e9381391d7",
        "byte_size": 440494,
        "width": 1440,
        "height": 1440,
        "format": "jpg",
        "status": "confirmed",
        "is_main": false,
        "public_url": "https://raw.githubusercontent.com/ajificemey278-ctrl/ozon-watch-product-catalog/main/products/longines/00234/5.jpg"
      },
      {
        "file": "6.jpg",
        "sha256": "dcc0015b363ce72cd1fda97be055173f29fa4f101e2fa000ee1914e0e68433a3",
        "byte_size": 463931,
        "width": 1440,
        "height": 1440,
        "format": "jpg",
        "status": "confirmed",
        "is_main": false,
        "public_url": "https://raw.githubusercontent.com/ajificemey278-ctrl/ozon-watch-product-catalog/main/products/longines/00234/6.jpg"
      },
      {
        "file": "7.jpg",
        "sha256": "1d211886436cf01cbee28b52e14614cdfa97b4575dc37a898a08b8c1436f0466",
        "byte_size": 527617,
        "width": 1440,
        "height": 1440,
        "format": "jpg",
        "status": "confirmed",
        "is_main": false,
        "public_url": "https://raw.githubusercontent.com/ajificemey278-ctrl/ozon-watch-product-catalog/main/products/longines/00234/7.jpg"
      },
      {
        "file": "8.jpg",
        "sha256": "adae0aadefdccc7a3d61abaa0af5b0e7c30fdccb4aff8e81c0ccc1a0a98fd5f1",
        "byte_size": 576193,
        "width": 1440,
        "height": 1440,
        "format": "jpg",
        "status": "confirmed",
        "is_main": false,
        "public_url": "https://raw.githubusercontent.com/ajificemey278-ctrl/ozon-watch-product-catalog/main/products/longines/00234/8.jpg"
      },
      {
        "file": "9.jpg",
        "sha256": "e50c25e93cf9c3f7294d74d46f3a126459d2c7c55ccf83e6bc0f1ab58207a8df",
        "byte_size": 361775,
        "width": 1440,
        "height": 1440,
        "format": "jpg",
        "status": "confirmed",
        "is_main": false,
        "public_url": "https://raw.githubusercontent.com/ajificemey278-ctrl/ozon-watch-product-catalog/main/products/longines/00234/9.jpg"
      }
    ]
  }
}
